django_lifecycle_flow/__init__.py
django_lifecycle_flow/decorators.py
django_lifecycle_flow/django_info.py
django_lifecycle_flow/hooks.py
django_lifecycle_flow/mixins.py
django_lifecycle_flow/models.py
django_lifecycle_flow-0.1.4.dist-info/LICENSE.md
django_lifecycle_flow-0.1.4.dist-info/WHEEL
django_lifecycle_flow-0.1.4.dist-info/METADATA
django_lifecycle_flow-0.1.4.dist-info/RECORD
