Metadata-Version: 2.1
Name: django-lifecycle-flow
Version: 0.1.4
Summary: 
Author: Osmar Perez Bautista
Author-email: osmarpb.97@gmail.com
Requires-Python: >=3.8,<4.0
Classifier: Programming Language :: Python :: 3
Classifier: Programming Language :: Python :: 3.10
Classifier: Programming Language :: Python :: 3.8
Classifier: Programming Language :: Python :: 3.9
Requires-Dist: Django (>=3.2)
Requires-Dist: packaging (>=21.3,<22.0)
Requires-Dist: urlman (>=2.0.1,<3.0.0)
